{
  "__entry_css_mods__": {
    "C:\\Users\\chumb\\Documents\\GitHub\\ti-2023-1-ti-2023-1_grupo_7\\src\\app\\page": [
      "C:\\Users\\chumb\\Documents\\GitHub\\ti-2023-1-ti-2023-1_grupo_7\\src\\app\\globals.css",
      "C:\\Users\\chumb\\Documents\\GitHub\\ti-2023-1-ti-2023-1_grupo_7\\src\\app\\styles\\Logo.css",
      "C:\\Users\\chumb\\Documents\\GitHub\\ti-2023-1-ti-2023-1_grupo_7\\src\\app\\Pages\\Home.css",
      "C:\\Users\\chumb\\Documents\\GitHub\\ti-2023-1-ti-2023-1_grupo_7\\src\\app\\styles\\NavBar.css",
      "C:\\Users\\chumb\\Documents\\GitHub\\ti-2023-1-ti-2023-1_grupo_7\\node_modules\\next\\font\\google\\target.css?{\"path\":\"src\\\\app\\\\components\\\\NavBar.js\",\"import\":\"Inter\",\"arguments\":[{\"subsets\":[\"latin\"]}],\"variableName\":\"inter\"}",
      "C:\\Users\\chumb\\Documents\\GitHub\\ti-2023-1-ti-2023-1_grupo_7\\src\\app\\styles\\ListaAtivos.css",
      "C:\\Users\\chumb\\Documents\\GitHub\\ti-2023-1-ti-2023-1_grupo_7\\node_modules\\next\\font\\google\\target.css?{\"path\":\"src\\\\app\\\\components\\\\ListaAtivos.js\",\"import\":\"Inter\",\"arguments\":[{\"subsets\":[\"latin\"]}],\"variableName\":\"inter\"}"
    ]
  },
  "C:\\Users\\chumb\\Documents\\GitHub\\ti-2023-1-ti-2023-1_grupo_7\\src\\app\\page.js": [
    "C:\\Users\\chumb\\Documents\\GitHub\\ti-2023-1-ti-2023-1_grupo_7\\src\\app\\styles\\Logo.css",
    "C:\\Users\\chumb\\Documents\\GitHub\\ti-2023-1-ti-2023-1_grupo_7\\node_modules\\next\\font\\google\\target.css?{\"path\":\"src\\\\app\\\\components\\\\NavBar.js\",\"import\":\"Inter\",\"arguments\":[{\"subsets\":[\"latin\"]}],\"variableName\":\"inter\"}",
    "C:\\Users\\chumb\\Documents\\GitHub\\ti-2023-1-ti-2023-1_grupo_7\\src\\app\\styles\\NavBar.css",
    "C:\\Users\\chumb\\Documents\\GitHub\\ti-2023-1-ti-2023-1_grupo_7\\node_modules\\next\\font\\google\\target.css?{\"path\":\"src\\\\app\\\\components\\\\ListaAtivos.js\",\"import\":\"Inter\",\"arguments\":[{\"subsets\":[\"latin\"]}],\"variableName\":\"inter\"}",
    "C:\\Users\\chumb\\Documents\\GitHub\\ti-2023-1-ti-2023-1_grupo_7\\src\\app\\styles\\ListaAtivos.css",
    "C:\\Users\\chumb\\Documents\\GitHub\\ti-2023-1-ti-2023-1_grupo_7\\src\\app\\Pages\\Home.css"
  ],
  "C:\\Users\\chumb\\Documents\\GitHub\\ti-2023-1-ti-2023-1_grupo_7\\src\\app\\layout.js": [
    "C:\\Users\\chumb\\Documents\\GitHub\\ti-2023-1-ti-2023-1_grupo_7\\src\\app\\globals.css"
  ]
}